darkcinder/__init__.py
mkdocs_darkcinder-0.0.2.dist-info/LICENSE.md
mkdocs_darkcinder-0.0.2.dist-info/METADATA
mkdocs_darkcinder-0.0.2.dist-info/WHEEL
mkdocs_darkcinder-0.0.2.dist-info/entry_points.txt
mkdocs_darkcinder-0.0.2.dist-info/top_level.txt
mkdocs_darkcinder-0.0.2.dist-info/RECORD
