Metadata-Version: 2.1
Name: mkdocs-darkcinder
Version: 0.0.2
Summary: A clean, responsive MkDocs theme - Forked from Cinder with ❤
Home-page: https://github.com/ziroau/darkcinder
Author: ziroAU
License: MIT
License-File: LICENSE.md
